termtrack/__init__.py
termtrack/body.py
termtrack/cli.py
termtrack/draw.py
termtrack/layer.py
termtrack/planets.py
termtrack/satellite.py
termtrack/data/earth.jpg
termtrack/data/mars.jpg
termtrack/data/moon.jpg
termtrack/data/ne_110m_land.dbf
termtrack/data/ne_110m_land.shp
termtrack/data/ne_110m_land.shx
termtrack/utils/__init__.py
termtrack/utils/curses.py
termtrack/utils/geometry.py
termtrack/utils/text.py
termtrack-0.7.4.dist-info/AUTHORS
termtrack-0.7.4.dist-info/LICENSE
termtrack-0.7.4.dist-info/METADATA
termtrack-0.7.4.dist-info/WHEEL
termtrack-0.7.4.dist-info/entry_points.txt
termtrack-0.7.4.dist-info/top_level.txt
termtrack-0.7.4.dist-info/RECORD
