Metadata-Version: 2.1
Name: termtrack
Version: 0.7.4
Summary: Track Earth-orbiting satellites from your terminal
Home-page: https://github.com/trehn/termtrack
Author: Torsten Rehn
Author-email: torsten@rehn.email
License: GPLv3
Keywords: terminal,track,tracking,satellite,orbit,iss
Classifier: Development Status :: 4 - Beta
Classifier: Environment :: Console :: Curses
Classifier: License :: OSI Approved :: GNU General Public License v3 (GPLv3)
Classifier: Natural Language :: English
Classifier: Operating System :: MacOS :: MacOS X
Classifier: Operating System :: POSIX
Classifier: Operating System :: Unix
Classifier: Programming Language :: Python :: 3
Classifier: Topic :: Utilities
License-File: LICENSE
License-File: AUTHORS
Requires-Dist: click (>=2.0)
Requires-Dist: Pillow (>=2.7.0)
Requires-Dist: pyephem (>=3.7.5.0)
Requires-Dist: pyshp (>=1.2.1)
Requires-Dist: requests (>=2.0.0)
